logextractx/__init__.py
logextractx/conftest.py
logextractx/djhuey.py
logextractx/flask.py
logextractx/formatter.py
logextractx/logger.py
logextractx/middleware.py
logextractx/test_formatter.py
logextractx/test_logger.py
logextractx/test_middleware.py
logextractx-0.3.0rc4.dist-info/LICENSE
logextractx-0.3.0rc4.dist-info/METADATA
logextractx-0.3.0rc4.dist-info/WHEEL
logextractx-0.3.0rc4.dist-info/top_level.txt
logextractx-0.3.0rc4.dist-info/RECORD
