Metadata-Version: 2.1
Name: logextractx
Version: 0.3.0rc4
Summary: LoggerAdapter, which helps you to propagate context information
Home-page: https://github.com/allegro/logextractx
Author: Maho (Lukasz Mach)
Author-email: lukasz.mach@allegro.pl
License: Apache License v 2.0
Platform: UNKNOWN
License-File: LICENSE
Requires-Dist: deprecation
